LICENSE.txt
MANIFEST.in
README.md
setup.py
autobump/__init__.py
autobump/__main__.py
autobump/capir.py
autobump/common.py
autobump/config.py
autobump/diff.py
autobump.egg-info/PKG-INFO
autobump.egg-info/SOURCES.txt
autobump.egg-info/dependency_links.txt
autobump.egg-info/entry_points.txt
autobump.egg-info/requires.txt
autobump.egg-info/top_level.txt
autobump/handlers/clojure.py
autobump/handlers/git.py
autobump/handlers/hg.py
autobump/handlers/java_ast.py
autobump/handlers/java_native.py
autobump/handlers/python.py
autobump/libexec/Inspector.java
autobump/libexec/TypeCompatibilityChecker.java
autobump/libexec/__init__.py
autobump/libexec/evalinspector.clj