Metadata-Version: 1.0
Name: autobump
Version: 0.2.0
Summary: Automatic semantic versioning of projects
Home-page: https://github.com/cshtarkov/autobump
Author: Christian Shtarkov
Author-email: cshtarkov@gmail.com
License: GPLv3
Platform: UNKNOWN
